<?xml version="1.0" encoding="UTF-8"?>
<!--
  ~ Copyright (C) 2001-2016 Food and Agriculture Organization of the
  ~ United Nations (FAO-UN), United Nations World Food Programme (WFP)
  ~ and United Nations Environment Programme (UNEP)
  ~
  ~ This program is free software; you can redistribute it and/or modify
  ~ it under the terms of the GNU General Public License as published by
  ~ the Free Software Foundation; either version 2 of the License, or (at
  ~ your option) any later version.
  ~
  ~ This program is distributed in the hope that it will be useful, but
  ~ WITHOUT ANY WARRANTY; without even the implied warranty of
  ~ MERCHANTABILITY or FITNESS FOR A PARTICULAR PURPOSE. See the GNU
  ~ General Public License for more details.
  ~
  ~ You should have received a copy of the GNU General Public License
  ~ along with this program; if not, write to the Free Software
  ~ Foundation, Inc., 51 Franklin St, Fifth Floor, Boston, MA 02110-1301, USA
  ~
  ~ Contact: Jeroen Ticheler - FAO - Viale delle Terme di Caracalla 2,
  ~ Rome - Italy. email: geonetwork@osgeo.org
  -->

<editor xmlns:xsi="http://www.w3.org/2001/XMLSchema-instance"
        xsi:noNamespaceSchemaLocation="../../config-editor.xsd"
        xmlns:gfc="http://www.isotc211.org/2005/gfc"
        xmlns:gco="http://www.isotc211.org/2005/gco"
        xmlns:gmx="http://www.isotc211.org/2005/gmx">

  <!-- Form field type configuration. Default is text. -->
  <fields>
    <for name="gfc:scope" use="textarea"/>
    <for name="gfc:fieldOfApplication" use="textarea"/>
    <for name="gfc:definition" use="textarea"/>
    <for name="gmx:scope" use="textarea"/>
    <for name="gmx:fieldOfApplication" use="textarea"/>

    <for name="gmx:language" use="data-gn-language-picker"/>
    <for name="gfc:functionalLanguage" use="data-gn-language-picker"/>
    <for name="gmd:languageCode" use="data-gn-language-picker"/>

    <for name="gfc:producer" addDirective="data-gn-directory-entry-selector"/>
  </fields>

  <fieldsWithFieldset>
    <name>gfc:producer</name>
    <name>gfc:carrierOfCharacteristics</name>
    <name>gfc:listedValue</name>
    <name>gfc:constrainedBy</name>
    <name>gfc:inheritsFrom</name>
    <name>gfc:inheritsTo</name>
  </fieldsWithFieldset>

  <!-- View configuration -->
  <views>
    <view name="default">
      <sidePanel>
        <directive gn-geo-publisher=""
                   data-ng-if="gnCurrentEdit.geoPublisherConfig"
                   data-config="{{gnCurrentEdit.geoPublisherConfig}}"
                   data-lang="lang"/>
        <directive data-gn-validation-report=""/>
        <directive data-gn-suggestion-list=""/>
        <directive data-gn-need-help="user-guide/describing-information/creating-metadata.html"/>
      </sidePanel>
      <tab id="default" default="true" mode="flat">
        <section name="gfc:FC_FeatureCatalogue">
          <field xpath="/gfc:FC_FeatureCatalogue/gmx:name"/>
          <field xpath="/gfc:FC_FeatureCatalogue/gmx:versionNumber"/>
          <field xpath="/gfc:FC_FeatureCatalogue/gmx:versionDate"/>
          <field
            xpath="/gfc:FC_FeatureCatalogue/gfc:featureType/gfc:FC_FeatureType/gfc:carrierOfCharacteristics"
            or="carrierOfCharacteristics"
            in="/gfc:FC_FeatureCatalogue/gfc:featureType/gfc:FC_FeatureType"/>
        </section>
      </tab>
      <flatModeExceptions>
        <for name="gfc:listedValue"/>
      </flatModeExceptions>
    </view>
    <view name="advanced">
      <tab id="advanced">
        <section xpath="/gfc:FC_FeatureType"/>
        <section xpath="/gfc:FC_FeatureCatalogue"/>
      </tab>
    </view>
    <view name="xml">
      <tab id="xml" default="true"/>
    </view>
  </views>
</editor>
